mopp/__init__.py
mopp/_defaults.py
mopp/mopp.py
mopp/modules/__init__.py
mopp/modules/align.py
mopp/modules/coverages.py
mopp/modules/features.py
mopp/modules/index.py
mopp/modules/metadata.py
mopp/modules/trim.py
mopp/modules/utils.py
mopp-0.0.1.dist-info/LICENSE
mopp-0.0.1.dist-info/METADATA
mopp-0.0.1.dist-info/WHEEL
mopp-0.0.1.dist-info/entry_points.txt
mopp-0.0.1.dist-info/top_level.txt
mopp-0.0.1.dist-info/RECORD
